rayx.cpython-314t-x86_64-linux-gnu.so
include/alpaka/alpaka.hpp
include/alpaka/version.hpp
include/alpaka/acc/AccCpuOmp2Blocks.hpp
include/alpaka/acc/AccCpuOmp2Threads.hpp
include/alpaka/acc/AccCpuSerial.hpp
include/alpaka/acc/AccCpuSycl.hpp
include/alpaka/acc/AccCpuTbbBlocks.hpp
include/alpaka/acc/AccCpuThreads.hpp
include/alpaka/acc/AccDevProps.hpp
include/alpaka/acc/AccFpgaSyclIntel.hpp
include/alpaka/acc/AccGenericSycl.hpp
include/alpaka/acc/AccGpuCudaRt.hpp
include/alpaka/acc/AccGpuHipRt.hpp
include/alpaka/acc/AccGpuSyclIntel.hpp
include/alpaka/acc/AccGpuUniformCudaHipRt.hpp
include/alpaka/acc/Tag.hpp
include/alpaka/acc/TagAccIsEnabled.hpp
include/alpaka/acc/Traits.hpp
include/alpaka/atomic/AtomicAtomicRef.hpp
include/alpaka/atomic/AtomicCpu.hpp
include/alpaka/atomic/AtomicGenericSycl.hpp
include/alpaka/atomic/AtomicHierarchy.hpp
include/alpaka/atomic/AtomicNoOp.hpp
include/alpaka/atomic/AtomicOmpBuiltIn.hpp
include/alpaka/atomic/AtomicStdLibLock.hpp
include/alpaka/atomic/AtomicUniformCudaHip.hpp
include/alpaka/atomic/AtomicUniformCudaHipBuiltIn.hpp
include/alpaka/atomic/Op.hpp
include/alpaka/atomic/Traits.hpp
include/alpaka/block/shared/dyn/BlockSharedDynMemberAllocKiB.hpp
include/alpaka/block/shared/dyn/BlockSharedMemDynGenericSycl.hpp
include/alpaka/block/shared/dyn/BlockSharedMemDynMember.hpp
include/alpaka/block/shared/dyn/BlockSharedMemDynUniformCudaHipBuiltIn.hpp
include/alpaka/block/shared/dyn/Traits.hpp
include/alpaka/block/shared/st/BlockSharedMemStGenericSycl.hpp
include/alpaka/block/shared/st/BlockSharedMemStMember.hpp
include/alpaka/block/shared/st/BlockSharedMemStMemberMasterSync.hpp
include/alpaka/block/shared/st/BlockSharedMemStUniformCudaHipBuiltIn.hpp
include/alpaka/block/shared/st/Traits.hpp
include/alpaka/block/shared/st/detail/BlockSharedMemStMemberImpl.hpp
include/alpaka/block/sync/BlockSyncBarrierOmp.hpp
include/alpaka/block/sync/BlockSyncBarrierThread.hpp
rayx-0.4.2.dist-info/METADATA
rayx-0.4.2.dist-info/WHEEL
rayx-0.4.2.dist-info/RECORD
rayx-0.4.2.dist-info/licenses/LICENSE
rayx-0.4.2.dist-info/sboms/auditwheel.cdx.json
