Metadata-Version: 2.2
Name: rayx
Version: 0.4.2
Summary: Python bindings for RAYX
Author-Email: RAYX team <rayx-support@helmholtz-berlin.de>
Maintainer-Email: RAYX team <rayx-support@helmholtz-berlin.de>
License: MIT License
Requires-Python: >=3.7
Requires-Dist: numpy>=2.0.0
